<?xml version="1.0" encoding="UTF-8"?>
<verification-metadata xmlns="https://schema.gradle.org/dependency-verification" xmlns:xsi="http://www.w3.org/2001/XMLSchema-instance" xsi:schemaLocation="https://schema.gradle.org/dependency-verification https://schema.gradle.org/dependency-verification/dependency-verification-1.2.xsd">
   <configuration>
      <verify-metadata>true</verify-metadata>
      <verify-signatures>true</verify-signatures>
      <ignored-keys>
         <ignored-key id="40273efc89f6f039" reason="Key couldn't be downloaded from any key server"/>
         <ignored-key id="de6547aef2ee7720" reason="Key couldn't be downloaded from any key server"/>
         <ignored-key id="fefe78456eddc34a" reason="Key couldn't be downloaded from any key server"/>
         <ignored-key id="8118b3bcdb1a5000" reason="Key couldn't be downloaded from any key server"/>
         <ignored-key id="c2148900bcd3c2af" reason="Key couldn't be downloaded from any key server"/>
         <ignored-key id="cb43338e060cf9fa" reason="Key couldn't be downloaded from any key server"/>
         <ignored-key id="7ecbd740ff06aeb5" reason="Key couldn't be downloaded from any key server"/>
         <ignored-key id="e7ae839cd7c58886" reason="Key couldn't be downloaded from any key server"/>
         <ignored-key id="6a0975f8b1127b83" reason="Key couldn't be downloaded from any key server"/>
         <ignored-key id="0374cf2e8dd1bdfd" reason="Key couldn't be downloaded from any key server"/>
      </ignored-keys>
      <trusted-keys>
         <trusted-key id="073f7a9345756f3b40cdb99e6c70a3b7599c5736" group="org.fusesource.jansi" name="jansi" version="2.4.1"/>
         <trusted-key id="0785b3eff60b1b1bea94e0bb7c25280eae63ebe5" group="org.apache.httpcomponents"/>
         <trusted-key id="0cc641c3a62453ab390066c4a41f13c999945293" group="commons-logging" name="commons-logging" version="1.2"/>
         <trusted-key id="0d35d3f60078655126908e8af3d1600878e85a3d" group="io.netty"/>
         <trusted-key id="0e6e990fd54e8532780086612b183b279dfd639e" group="com.typesafe" name="config" version="1.4.3"/>
         <trusted-key id="19beab2d799c020f17c69126b16698a4adf4d638" group="org.checkerframework" name="checker-qual" version="3.33.0"/>
         <trusted-key id="28118c070cb22a0175a2e8d43d12ca2ac19f3181" group="^com[.]fasterxml($|([.].*))" regex="true"/>
         <trusted-key id="2b1042677fd8190c7b9fc0dc2161d72e7dcd4258" group="^org[.]sonarsource($|([.].*))" regex="true"/>
         <trusted-key id="2db4f1ef0fa761ecc4ea935c86fdc7e2a11262cb">
            <trusting group="commons-codec"/>
            <trusting group="commons-io"/>
            <trusting group="org.apache.commons"/>
         </trusted-key>
         <trusted-key id="2e3a1affe42b5f53af19f780bcf4173966770193" group="org.jetbrains" name="annotations" version="13.0"/>
         <trusted-key id="2f528d36d67b69edf998d85778bd65473cb3bd13" group="com.google.cloud.tools"/>
         <trusted-key id="47504b76cf89c15c0512d9afe16ab52d79fd224f" group="^com[.]google($|([.].*))" regex="true"/>
         <trusted-key id="4db1a49729b053caf015cee9a6adfc93ef34893e" group="org.hamcrest"/>
         <trusted-key id="5897253bea3046aeea95a067e93671c7272b7b3f" group="org.jdom" name="jdom2" version="2.0.6"/>
         <trusted-key id="600ea202b1ec682f4a788e5aac7a514bc9f9bb70" group="io.opencensus"/>
         <trusted-key id="60200ac4ae761f1614d6c46766d68daa073be985">
            <trusting group="ch.qos.logback"/>
            <trusting group="org.slf4j"/>
         </trusted-key>
         <trusted-key id="694621a7227d8d5289699830abe9f3126bb741c1" group="com.google.guava"/>
         <trusted-key id="6dd3b8c64ef75253beb2c53ad908a43fb7ec07ac" group="com.sun.activation"/>
         <trusted-key id="7616eb882daf57a11477aaf559a252fb1199d873" group="com.google.code.findbugs" name="jsr305" version="3.0.2"/>
         <trusted-key id="79156e0351af8604de9b186b09a79e1e15a04694" group="org.vafer" name="jdependency" version="2.7.0"/>
         <trusted-key id="7b121b76a7ed6ce6e60ad51784e913a8e3a748c0" group="org.bouncycastle" name="bcprov-jdk18on" version="1.78.1"/>
         <trusted-key id="7e22d50a7ebd9d2cd269b2d4056aca74d46000bf" group="io.netty"/>
         <trusted-key id="84789d24df77a32433ce1f079eb80e92eb2135b1" group="org.apache" name="apache"/>
         <trusted-key id="8756c4f765c9ac3cb6b85d62379ce192d401ab61" group="org.jetbrains.intellij.deps" name="trove4j" version="1.0.20200330"/>
         <trusted-key id="8e3a02905a1ae67e7b0f9acd3967d4eda591b991">
            <trusting group="io.ktor"/>
            <trusting group="org.jetbrains.kotlinx"/>
         </trusted-key>
         <trusted-key id="9d0a56aaa0d60e0c0c7dccc0b4c70893b62babe8" group="^org[.]apache[.]logging($|([.].*))" regex="true"/>
         <trusted-key id="a5bd02b93e7a40482eb1d66a5f69ad087600b22c" group="org.ow2.asm"/>
         <trusted-key id="a7892505cf1a58076453e52d7999befba1039e8b" group="net.bytebuddy"/>
         <trusted-key id="aed5ee6c45d0fe8d5d1b164f27ded4bf6216db8f" group="org.eclipse.jetty.alpn" name="alpn-api" version="1.1.3.v20160715"/>
         <trusted-key id="b02335aa54ccf21e52bbf9abd9c565aa72ba2fdd" group="io.grpc" name="grpc-context" version="1.27.2"/>
         <trusted-key id="b6e73d84ea4fcc47166087253faad2cd5ecbb314" group="org.apache.commons" name="commons-parent"/>
         <trusted-key id="bdb5fa4fe719d787fb3d3197f6d4a1d411e9d1ae" group="com.google.guava"/>
         <trusted-key id="c7be5bcc9fec15518cfda882b0f3710fa64900e7" group="^com[.]google($|([.].*))" regex="true"/>
         <trusted-key id="ce8075a251547bee249bc151a2115ae15f6b8b72" group="^org[.]apache($|([.].*))" regex="true"/>
         <trusted-key id="dbd744ace7ade6aa50dd591f66b50994442d2d40" group="^com[.]squareup($|([.].*))" regex="true"/>
         <trusted-key id="e5138a8e9f2e7e42d38b14d99aee152cdccebfcb" group="io.github.hakky54"/>
         <trusted-key id="e74d86e924b8c8873bf13a6bdcfc3946615ac718" group="javax.xml.bind" name="jaxb-api" version="2.2.4"/>
         <trusted-key id="e7dc75fc24fb3c8dfe8086ad3d5839a2262cbbfb" group="org.jetbrains.kotlinx"/>
         <trusted-key id="e85aed155021af8a6c6b7a4a7c7d8456294423ba" group="org.objenesis"/>
         <trusted-key id="eb1b3de71713c9ec2e87cc26ee92349ad86de446" group="com.google.j2objc" name="j2objc-annotations" version="2.8"/>
         <trusted-key id="ee0ca873074092f806f59b65d364abaa39a47320" group="com.google.errorprone"/>
         <trusted-key id="f046369b06b761ac86d9849f71b329993bffcfdd" group="^org[.]graalvm[.]buildtools($|([.].*))" regex="true"/>
         <trusted-key id="f254b35617dc255d9344bcfa873a8e86b4372146" group="org.codehaus.plexus"/>
         <trusted-key id="fa77dcfef2ee6eb2debedd2c012579464d01c06a" group="org.apache"/>
         <trusted-key id="fa7929f83ad44c4590f6cc6815c71c0a4e0b8edd" group="net.java.dev.jna"/>
         <trusted-key id="ff6e2c001948c5f2f38b0cc385911f425ec61b51">
            <trusting group="junit"/>
            <trusting group="org.junit"/>
            <trusting group="org.junit.jupiter"/>
            <trusting group="org.junit.platform"/>
            <trusting group="org.opentest4j"/>
         </trusted-key>
      </trusted-keys>
   </configuration>
   <components>
      <component group="com.github.johnrengelman.shadow" name="com.github.johnrengelman.shadow.gradle.plugin" version="7.1.2">
         <artifact name="com.github.johnrengelman.shadow.gradle.plugin-7.1.2.pom">
            <sha256 value="956e45085e52ea5ef32d34671ebb84eb1c41a83c4549af26e68635f1061798d3" origin="Generated by Gradle" reason="Artifact is not signed"/>
         </artifact>
      </component>
      <component group="com.google.cloud.tools" name="jib-gradle-plugin" version="3.4.1">
         <artifact name="jib-gradle-plugin-3.4.1.jar">
            <sha256 value="3437ce00a0db34d6ee04d38666121d281ed95470d2e205925fdb9543da132c45" origin="Generated by Gradle" reason="Artifact is not signed"/>
         </artifact>
         <artifact name="jib-gradle-plugin-3.4.1.module">
            <sha256 value="3567ed918436a69f4a847e38fd2cf129d26de773b655e812950841a4ef7b4cc9" origin="Generated by Gradle" reason="Artifact is not signed"/>
         </artifact>
      </component>
      <component group="com.google.j2objc" name="j2objc-annotations" version="1.3">
         <artifact name="j2objc-annotations-1.3.pom">
            <pgp value="b801e2f8ef035068ec1139cc29579f18fa8fd93b"/>
         </artifact>
      </component>
      <component group="com.jsoizo" name="kotlin-csv-jvm" version="1.10.0">
         <artifact name="kotlin-csv-jvm-1.10.0.jar">
            <sha256 value="b50dd087eeae97120d79c261ae063046c2407c1747e4ceeceffa735ad8f61df3" origin="Generated by Gradle" reason="A key couldn't be downloaded"/>
         </artifact>
         <artifact name="kotlin-csv-jvm-1.10.0.module">
            <sha256 value="32aa31734a43967778cfe7a2107c3a105a06a8e2149df283b156b4474850072c" origin="Generated by Gradle" reason="A key couldn't be downloaded"/>
         </artifact>
      </component>
      <component group="com.sun.istack" name="istack-commons" version="3.0.11">
         <artifact name="istack-commons-3.0.11.pom">
            <sha256 value="5c56b5d995649a720b1275d98bdf18eb538cd965f75155edf6663bd9079883ef" origin="Generated by Gradle" reason="A key couldn't be downloaded"/>
         </artifact>
      </component>
      <component group="com.sun.istack" name="istack-commons-runtime" version="3.0.11">
         <artifact name="istack-commons-runtime-3.0.11-sources.jar">
            <sha256 value="5650575de0e53cd845820332eb67fda19a8a064d324cc6cf16c6f85f957664c5" origin="Generated by Gradle" reason="A key couldn't be downloaded"/>
         </artifact>
         <artifact name="istack-commons-runtime-3.0.11.jar">
            <sha256 value="cc3f3704ca7bf23e97653edcfc6bbcf9bfe3866b8aed7f290ae7809085d3a959" origin="Generated by Gradle" reason="A key couldn't be downloaded"/>
         </artifact>
         <artifact name="istack-commons-runtime-3.0.11.pom">
            <sha256 value="ae1c070432a8cc35b92960758175014e991193af982e0ad083e40885611d7e94" origin="Generated by Gradle" reason="A key couldn't be downloaded"/>
         </artifact>
      </component>
      <component group="com.sun.xml.bind" name="jaxb-bom-ext" version="2.3.3">
         <artifact name="jaxb-bom-ext-2.3.3.pom">
            <sha256 value="1b02bd4272f2ade47f0e825264c435171cd3e09d11b23bbab8cc8421b3e83398" origin="Generated by Gradle" reason="A key couldn't be downloaded"/>
         </artifact>
      </component>
      <component group="com.sun.xml.bind.mvn" name="jaxb-parent" version="2.3.3">
         <artifact name="jaxb-parent-2.3.3.pom">
            <sha256 value="44ccfeebbcf6745d38efbcc68e924cbf19907afd7e7b258c67e9895474880921" origin="Generated by Gradle" reason="A key couldn't be downloaded"/>
         </artifact>
      </component>
      <component group="com.sun.xml.bind.mvn" name="jaxb-runtime-parent" version="2.3.3">
         <artifact name="jaxb-runtime-parent-2.3.3.pom">
            <sha256 value="679f0e8b0c2ebcabc0ead871a032819d669d399af1fb30dfb279f10b037785cd" origin="Generated by Gradle" reason="A key couldn't be downloaded"/>
         </artifact>
      </component>
      <component group="com.sun.xml.bind.mvn" name="jaxb-txw-parent" version="2.3.3">
         <artifact name="jaxb-txw-parent-2.3.3.pom">
            <sha256 value="3cccb8664bf3838baeb2fe605552950e40721e8982c2072d2ce9976d3c79409a" origin="Generated by Gradle" reason="A key couldn't be downloaded"/>
         </artifact>
      </component>
      <component group="gradle.plugin.com.github.johnrengelman" name="shadow" version="7.1.2">
         <artifact name="shadow-7.1.2.jar">
            <sha256 value="bf705cc2ea5c0180aa870a0fa80b39bf13a14d27128e1eb3a4b674be34f58e90" origin="Generated by Gradle" reason="Artifact is not signed"/>
         </artifact>
         <artifact name="shadow-7.1.2.pom">
            <sha256 value="1faab0be417d7b3c41a97cca0aca8a5b0b6406fc3b12d7f28e2c34131dff934a" origin="Generated by Gradle" reason="Artifact is not signed"/>
         </artifact>
      </component>
      <component group="io.ktor.plugin" name="io.ktor.plugin.gradle.plugin" version="2.3.12">
         <artifact name="io.ktor.plugin.gradle.plugin-2.3.12.pom">
            <sha256 value="15bba3ad36658c42e735ce589ac11ea680e0d2ce1b15e34b2b20dd5b3e1fbebe" origin="Generated by Gradle" reason="Artifact is not signed"/>
         </artifact>
      </component>
      <component group="io.ktor.plugin" name="plugin" version="2.3.12">
         <artifact name="plugin-2.3.12.jar">
            <sha256 value="862e24416ffac43ddd91f92f34c5a71e3535f8f4eae8ec0b78051b92365fa537" origin="Generated by Gradle" reason="Artifact is not signed"/>
         </artifact>
         <artifact name="plugin-2.3.12.module">
            <sha256 value="80b2ae0a27a239b77a572d0ea0203d938c77aa3f7cea4ae11a533fc694fd775f" origin="Generated by Gradle" reason="Artifact is not signed"/>
         </artifact>
      </component>
      <component group="io.mockk" name="mockk" version="1.13.12">
         <artifact name="mockk-1.13.12.module">
            <sha256 value="1d699d3be5ca29d29aab12205ab0418e6f4740b08a05da7331013d71878a1cac" origin="Generated by Gradle" reason="A key couldn't be downloaded"/>
         </artifact>
         <artifact name="mockk-metadata-1.13.12.jar">
            <sha256 value="f634a6723d70211de75070491bc7062b042f8dc01bcd3b88487fcb1a5b6d1c1c" origin="Generated by Gradle" reason="A key couldn't be downloaded"/>
         </artifact>
      </component>
      <component group="io.mockk" name="mockk-agent" version="1.13.12">
         <artifact name="mockk-agent-1.13.12.module">
            <sha256 value="c7daa1310489506f5aa7cafbd10ec916f7192b93bcb84113d855209f3b2c8aa7" origin="Generated by Gradle" reason="A key couldn't be downloaded"/>
         </artifact>
         <artifact name="mockk-agent-metadata-1.13.12.jar">
            <sha256 value="b5a3d62e5446d89a2a8ede3a05664f3f90e9d1373305fcd046e706dd9fae3c00" origin="Generated by Gradle" reason="A key couldn't be downloaded"/>
         </artifact>
      </component>
      <component group="io.mockk" name="mockk-agent-api" version="1.13.12">
         <artifact name="mockk-agent-api-1.13.12.module">
            <sha256 value="47a415a9e6103ea3216be041f01c3eec7e4c32a727a4ca0b76af7764b950029f" origin="Generated by Gradle" reason="A key couldn't be downloaded"/>
         </artifact>
         <artifact name="mockk-agent-api-metadata-1.13.12.jar">
            <sha256 value="fbc64f5c44a7added8b6eab517cf7d70555e25153bf5d44a6ed9b0e5312f7de9" origin="Generated by Gradle" reason="A key couldn't be downloaded"/>
         </artifact>
      </component>
      <component group="io.mockk" name="mockk-agent-api-jvm" version="1.13.12">
         <artifact name="mockk-agent-api-jvm-1.13.12.jar">
            <sha256 value="6aba1cfaba319bdbf624990a3a795ec59d8f71ca7f1bfc34487660fd9f403724" origin="Generated by Gradle" reason="A key couldn't be downloaded"/>
         </artifact>
         <artifact name="mockk-agent-api-jvm-1.13.12.module">
            <sha256 value="a003be63bb2604eb50d50086b9f759a58fdd1f142a6a5b381f293c2a25222674" origin="Generated by Gradle" reason="A key couldn't be downloaded"/>
         </artifact>
      </component>
      <component group="io.mockk" name="mockk-agent-jvm" version="1.13.12">
         <artifact name="mockk-agent-jvm-1.13.12.jar">
            <sha256 value="a016a7d678a37966ef6a91dd3f5c0d901e1fd087ea3a664b8aaade02edbb0428" origin="Generated by Gradle" reason="A key couldn't be downloaded"/>
         </artifact>
         <artifact name="mockk-agent-jvm-1.13.12.module">
            <sha256 value="c9d7ff12c7a44ccaff8d4eb1788be145ae9c4c4491598f0b78ed1676be18375c" origin="Generated by Gradle" reason="A key couldn't be downloaded"/>
         </artifact>
      </component>
      <component group="io.mockk" name="mockk-core" version="1.13.12">
         <artifact name="mockk-core-1.13.12.module">
            <sha256 value="090abada9b4d49947bcc4f0cc888a8594214f71b7421b2d82aea9a751ac32be9" origin="Generated by Gradle" reason="A key couldn't be downloaded"/>
         </artifact>
         <artifact name="mockk-core-metadata-1.13.12.jar">
            <sha256 value="fbc64f5c44a7added8b6eab517cf7d70555e25153bf5d44a6ed9b0e5312f7de9" origin="Generated by Gradle" reason="A key couldn't be downloaded"/>
         </artifact>
      </component>
      <component group="io.mockk" name="mockk-core-jvm" version="1.13.12">
         <artifact name="mockk-core-jvm-1.13.12.jar">
            <sha256 value="55438756521253b04da99f8e559d99188edb3efc08c5735820ff5c72eeef4f0e" origin="Generated by Gradle" reason="A key couldn't be downloaded"/>
         </artifact>
         <artifact name="mockk-core-jvm-1.13.12.module">
            <sha256 value="737ce4494be092260bc48191b5ea9c988018cd5e752adcbc8c8a2625f21e076a" origin="Generated by Gradle" reason="A key couldn't be downloaded"/>
         </artifact>
      </component>
      <component group="io.mockk" name="mockk-dsl" version="1.13.12">
         <artifact name="mockk-dsl-1.13.12.module">
            <sha256 value="c288d83c098fa45eb0f2fe14ce7df10e211d4ed3c91d1366ad16259f800aa0fa" origin="Generated by Gradle" reason="A key couldn't be downloaded"/>
         </artifact>
         <artifact name="mockk-dsl-metadata-1.13.12.jar">
            <sha256 value="fbc64f5c44a7added8b6eab517cf7d70555e25153bf5d44a6ed9b0e5312f7de9" origin="Generated by Gradle" reason="A key couldn't be downloaded"/>
         </artifact>
      </component>
      <component group="io.mockk" name="mockk-dsl-jvm" version="1.13.12">
         <artifact name="mockk-dsl-jvm-1.13.12.jar">
            <sha256 value="869713aea27e0d589767172ed05b8319da4853b8686fcfbdbae9a4dbd1160ae4" origin="Generated by Gradle" reason="A key couldn't be downloaded"/>
         </artifact>
         <artifact name="mockk-dsl-jvm-1.13.12.module">
            <sha256 value="79119281c4487833011558f5a1157341ffd0a8a09c139fdcc9dbcc50c657b532" origin="Generated by Gradle" reason="A key couldn't be downloaded"/>
         </artifact>
      </component>
      <component group="io.mockk" name="mockk-jvm" version="1.13.12">
         <artifact name="mockk-jvm-1.13.12-sources.jar">
            <sha256 value="bf9c367624b262bea92fa27cd49125f8657eec9b9a95677c3bb19aae5658823f" origin="Generated by Gradle" reason="A key couldn't be downloaded"/>
         </artifact>
         <artifact name="mockk-jvm-1.13.12.jar">
            <sha256 value="d5e00099ecc52e171a6eb90af9bdeea8648fc0386eb66753f5b2ac41257ad2d1" origin="Generated by Gradle" reason="A key couldn't be downloaded"/>
         </artifact>
         <artifact name="mockk-jvm-1.13.12.module">
            <sha256 value="c6bdbf723dabb47e730b153fc45e52bafb9c2cfb04f13bb17f364df6a43aae45" origin="Generated by Gradle" reason="A key couldn't be downloaded"/>
         </artifact>
      </component>
      <component group="jakarta.xml.bind" name="jakarta.xml.bind-api" version="2.3.3">
         <artifact name="jakarta.xml.bind-api-2.3.3-sources.jar">
            <sha256 value="6da17f357f2e37a53ddeefb2d7445c1da550e50119fe87e0b4c7f275dc48b3cb" origin="Generated by Gradle" reason="A key couldn't be downloaded"/>
         </artifact>
         <artifact name="jakarta.xml.bind-api-2.3.3.jar">
            <sha256 value="c04539f472e9a6dd0c7685ea82d677282269ab8e7baca2e14500e381e0c6cec5" origin="Generated by Gradle" reason="A key couldn't be downloaded"/>
         </artifact>
         <artifact name="jakarta.xml.bind-api-2.3.3.pom">
            <sha256 value="7fe2ca5dce4b14a646bbf921d13ca42caf2a2c0654da155c7563865c989396fd" origin="Generated by Gradle" reason="A key couldn't be downloaded"/>
         </artifact>
      </component>
      <component group="jakarta.xml.bind" name="jakarta.xml.bind-api-parent" version="2.3.3">
         <artifact name="jakarta.xml.bind-api-parent-2.3.3.pom">
            <sha256 value="280da531760166d4412368d0dd899ef4aebfd0a7d82bf233502e29856806ada9" origin="Generated by Gradle" reason="A key couldn't be downloaded"/>
         </artifact>
      </component>
      <component group="javax.activation" name="activation" version="1.1">
         <artifact name="activation-1.1-sources.jar">
            <sha256 value="d1ce2ec5b4fa82d2424e38bb4efd75539f87b7e22e8c38c95cef541ef82fb037" origin="Generated by Gradle" reason="Artifact is not signed"/>
         </artifact>
         <artifact name="activation-1.1.jar">
            <sha256 value="2881c79c9d6ef01c58e62beea13e9d1ac8b8baa16f2fc198ad6e6776defdcdd3" origin="Generated by Gradle" reason="Artifact is not signed"/>
         </artifact>
         <artifact name="activation-1.1.pom">
            <sha256 value="d490e540a11504b9d71718b1c85fef7b3de6802361290824539b076d58faa8a0" origin="Generated by Gradle" reason="Artifact is not signed"/>
         </artifact>
      </component>
      <component group="javax.xml.stream" name="stax-api" version="1.0-2">
         <artifact name="stax-api-1.0-2-sources.jar">
            <sha256 value="70b50265565dbbeb70ee3368c50e00220f8644da7a48bd67952c404e2bb0fd16" origin="Generated by Gradle" reason="Artifact is not signed"/>
         </artifact>
         <artifact name="stax-api-1.0-2.jar">
            <sha256 value="e8c70ebd76f982c9582a82ef82cf6ce14a7d58a4a4dca5cb7b7fc988c80089b7" origin="Generated by Gradle" reason="Artifact is not signed"/>
         </artifact>
         <artifact name="stax-api-1.0-2.pom">
            <sha256 value="2864f19da84fd52763d75a197a71779b2decbccaac3eb4e4760ffc884c5af4a2" origin="Generated by Gradle" reason="Artifact is not signed"/>
         </artifact>
      </component>
      <component group="net.java" name="jvnet-parent" version="1">
         <artifact name="jvnet-parent-1.pom">
            <sha256 value="281440811268e65d9e266b3cc898297e214e04f09740d0386ceeb4a8923d63bf" origin="Generated by Gradle" reason="A key couldn't be downloaded"/>
         </artifact>
      </component>
      <component group="net.mamoe.yamlkt" name="yamlkt" version="0.13.0">
         <artifact name="yamlkt-0.13.0.module">
            <sha256 value="e0ebb6e3d9431c94abe7560c43ddc7399b9c51fd4a9c9c8e6e4e44a104097895" origin="Generated by Gradle" reason="A key couldn't be downloaded"/>
         </artifact>
         <artifact name="yamlkt-metadata-0.13.0-all.jar">
            <sha256 value="c84cfff99808746455a63e9cc02939b7185e709e0fdd342c486a4e9f1f39f7aa" origin="Generated by Gradle" reason="A key couldn't be downloaded"/>
         </artifact>
      </component>
      <component group="net.mamoe.yamlkt" name="yamlkt-jvm" version="0.13.0">
         <artifact name="yamlkt-jvm-0.13.0.jar">
            <sha256 value="78b1e79271a8d9fe9b9733488fde2c0724a7bde6725ccab97df9b8c3f09f6919" origin="Generated by Gradle" reason="A key couldn't be downloaded"/>
         </artifact>
         <artifact name="yamlkt-jvm-0.13.0.module">
            <sha256 value="7310727618c3b59dcc963909eec38e60271c3667b965cfba929609487ec1ce71" origin="Generated by Gradle" reason="A key couldn't be downloaded"/>
         </artifact>
      </component>
      <component group="org.apache" name="apache" version="13">
         <artifact name="apache-13.pom">
            <pgp value="f254b35617dc255d9344bcfa873a8e86b4372146"/>
         </artifact>
      </component>
      <component group="org.apache" name="apache" version="18">
         <artifact name="apache-18.pom">
            <pgp value="190d5a957ff22273e601f7a7c92c5fec70161c62"/>
         </artifact>
      </component>
      <component group="org.apache.commons" name="commons-parent" version="34">
         <artifact name="commons-parent-34.pom">
            <pgp value="d6f1bc78607808ec8e9f69437a8860944fad5f62"/>
         </artifact>
      </component>
      <component group="org.codehaus.plexus" name="plexus" version="8">
         <artifact name="plexus-8.pom">
            <pgp value="fa77dcfef2ee6eb2debedd2c012579464d01c06a"/>
         </artifact>
      </component>
      <component group="org.eclipse.ee4j" name="project" version="1.0.6">
         <artifact name="project-1.0.6.pom">
            <pgp value="aa70c7c433d501636392ec02153e7a3c2b4e5118"/>
         </artifact>
      </component>
      <component group="org.eclipse.jetty" name="jetty-parent" version="21">
         <artifact name="jetty-parent-21.pom">
            <sha256 value="7972e9ec6f3852a8ee1ee5d4d10dcc9dcd6077b125f935aa96b367a6c82337f5" origin="Generated by Gradle" reason="A key couldn't be downloaded"/>
         </artifact>
      </component>
      <component group="org.fusesource" name="fusesource-pom" version="1.12">
         <artifact name="fusesource-pom-1.12.pom">
            <sha256 value="c40d960daadcef7b01c1b1c6657afbac4fffb5e53168f8fcb0b28b84e6fdcca1" origin="Generated by Gradle" reason="Artifact is not signed"/>
         </artifact>
      </component>
      <component group="org.glassfish.jaxb" name="jaxb-bom" version="2.3.3">
         <artifact name="jaxb-bom-2.3.3.pom">
            <sha256 value="123381e4250f4595375e72fdc0923203562e3d8e782b94f08b192d955ae2e2e0" origin="Generated by Gradle" reason="A key couldn't be downloaded"/>
         </artifact>
      </component>
      <component group="org.glassfish.jaxb" name="jaxb-runtime" version="2.3.3">
         <artifact name="jaxb-runtime-2.3.3-sources.jar">
            <sha256 value="b9823638ac81797d0dfd12f5371f13b05386c254b81817ef7b4a27f0aba1863b" origin="Generated by Gradle" reason="A key couldn't be downloaded"/>
         </artifact>
         <artifact name="jaxb-runtime-2.3.3.jar">
            <sha256 value="3fcbf9247b08303ecaef2b8b91b47e220b6eced843e02837a5379d011c2c623d" origin="Generated by Gradle" reason="A key couldn't be downloaded"/>
         </artifact>
         <artifact name="jaxb-runtime-2.3.3.pom">
            <sha256 value="92dfe5a3925a9194f0a348ca7a4d5ae7dc64fca79ceab5bcd04ef947f42f36f4" origin="Generated by Gradle" reason="A key couldn't be downloaded"/>
         </artifact>
      </component>
      <component group="org.glassfish.jaxb" name="txw2" version="2.3.3">
         <artifact name="txw2-2.3.3-sources.jar">
            <sha256 value="1775bb2c62fdd258c1649deea3daf43ad41784a182319eeeeb70c020dd812660" origin="Generated by Gradle" reason="A key couldn't be downloaded"/>
         </artifact>
         <artifact name="txw2-2.3.3.jar">
            <sha256 value="97de89031348fced8d8d58b9c288c2185ab07bedc7a591f070377c45ddb05fee" origin="Generated by Gradle" reason="A key couldn't be downloaded"/>
         </artifact>
         <artifact name="txw2-2.3.3.pom">
            <sha256 value="578621ff5ae4feaf6e41c3e0575ba67db3aa57aeb70ed68611795cddfb4b577f" origin="Generated by Gradle" reason="A key couldn't be downloaded"/>
         </artifact>
      </component>
      <component group="org.jacoco" name="org.jacoco.agent" version="0.8.9">
         <artifact name="org.jacoco.agent-0.8.9.jar">
            <sha256 value="c067e29a49063220e75215eff1bc234584ad002e747afdf13a69662be5b0e07d" origin="Generated by Gradle" reason="A key couldn't be downloaded"/>
         </artifact>
         <artifact name="org.jacoco.agent-0.8.9.pom">
            <sha256 value="81e44bb0641819c08e37dc46d6f72453259812efc8ddf21961d505c8c2b50ecc" origin="Generated by Gradle" reason="A key couldn't be downloaded"/>
         </artifact>
      </component>
      <component group="org.jacoco" name="org.jacoco.ant" version="0.8.9">
         <artifact name="org.jacoco.ant-0.8.9.jar">
            <sha256 value="5695ecd24f04c421b12a74f4b44042857b16eed0bc049ff38dd6dc40abca7bef" origin="Generated by Gradle" reason="A key couldn't be downloaded"/>
         </artifact>
         <artifact name="org.jacoco.ant-0.8.9.pom">
            <sha256 value="9fa03278406b7cd5cf4d4c7a03469efec0c94cd46fe13436f6dd0c25f3b14de8" origin="Generated by Gradle" reason="A key couldn't be downloaded"/>
         </artifact>
      </component>
      <component group="org.jacoco" name="org.jacoco.build" version="0.8.9">
         <artifact name="org.jacoco.build-0.8.9.pom">
            <sha256 value="02678f267cdaa23ff51772ad1f033a1f3ff5741cc10d444740bd4834d47583b3" origin="Generated by Gradle" reason="A key couldn't be downloaded"/>
         </artifact>
      </component>
      <component group="org.jacoco" name="org.jacoco.core" version="0.8.9">
         <artifact name="org.jacoco.core-0.8.9.jar">
            <sha256 value="a33e041dd97530ea57d6dde0e2635ea51680827d2dc0de372d3ccc45b51e68c7" origin="Generated by Gradle" reason="A key couldn't be downloaded"/>
         </artifact>
         <artifact name="org.jacoco.core-0.8.9.pom">
            <sha256 value="5404f7052765a64374d275367fd9485bb5996b369113c89a8557d8f024810f02" origin="Generated by Gradle" reason="A key couldn't be downloaded"/>
         </artifact>
      </component>
      <component group="org.jacoco" name="org.jacoco.report" version="0.8.9">
         <artifact name="org.jacoco.report-0.8.9.jar">
            <sha256 value="0d36b87cdea59f98c8cf26367003b4735d5c3187411d4649ddfefdeed387b63e" origin="Generated by Gradle" reason="A key couldn't be downloaded"/>
         </artifact>
         <artifact name="org.jacoco.report-0.8.9.pom">
            <sha256 value="81e413bdde52bc70ae63f5cb14e524e5691532db7779b55d5899ee5c0b6fb871" origin="Generated by Gradle" reason="A key couldn't be downloaded"/>
         </artifact>
      </component>
      <component group="org.jetbrains" name="annotations" version="23.0.0">
         <artifact name="annotations-23.0.0.jar">
            <sha256 value="7b0f19724082cbfcbc66e5abea2b9bc92cf08a1ea11e191933ed43801eb3cd05" origin="Generated by Gradle" reason="A key couldn't be downloaded"/>
         </artifact>
         <artifact name="annotations-23.0.0.pom">
            <sha256 value="c9490f655132328df2cfbcfdf743f53fc3916d6c1d10437175a6ca6e3a67771c" origin="Generated by Gradle" reason="A key couldn't be downloaded"/>
         </artifact>
      </component>
      <component group="org.jetbrains.kotlin" name="kotlin-build-common" version="2.0.0">
         <artifact name="kotlin-build-common-2.0.0.jar">
            <sha256 value="26868d37837621259993cd8b4587bfffae86b17e4f211d5baa0bf605248a2412" origin="Generated by Gradle" reason="A key couldn't be downloaded"/>
         </artifact>
         <artifact name="kotlin-build-common-2.0.0.pom">
            <sha256 value="370f9ceb7c9621495447874109c586f58308b945b9d921d87af5bbb48df54d35" origin="Generated by Gradle" reason="A key couldn't be downloaded"/>
         </artifact>
      </component>
      <component group="org.jetbrains.kotlin" name="kotlin-build-statistics" version="2.0.0">
         <artifact name="kotlin-build-statistics-2.0.0.jar">
            <sha256 value="f089b5f057f7c78630107bf4661f75b68cf1ce7492f415bdf2b50bc2b47ef815" origin="Generated by Gradle" reason="A key couldn't be downloaded"/>
         </artifact>
         <artifact name="kotlin-build-statistics-2.0.0.pom">
            <sha256 value="9ac80f8df65172a45f80f5b421001377098133b7cb5d73387cffbf2b2239be69" origin="Generated by Gradle" reason="A key couldn't be downloaded"/>
         </artifact>
      </component>
      <component group="org.jetbrains.kotlin" name="kotlin-build-tools-api" version="2.0.0">
         <artifact name="kotlin-build-tools-api-2.0.0.jar">
            <sha256 value="8be57288054decd4bca5a2dcb89e4e8e896c2520e45a2488765d813ffd229f11" origin="Generated by Gradle" reason="A key couldn't be downloaded"/>
         </artifact>
         <artifact name="kotlin-build-tools-api-2.0.0.pom">
            <sha256 value="cc39e9e0c9bbeec5a0ccfe0a78734c541c00fca3027c6de8ebc13bade0f5400b" origin="Generated by Gradle" reason="A key couldn't be downloaded"/>
         </artifact>
      </component>
      <component group="org.jetbrains.kotlin" name="kotlin-build-tools-impl" version="2.0.0">
         <artifact name="kotlin-build-tools-impl-2.0.0.jar">
            <sha256 value="551cce7299ed378a4fed97e6c26179af10f18b7b263f9599ae0086faa160446b" origin="Generated by Gradle" reason="A key couldn't be downloaded"/>
         </artifact>
         <artifact name="kotlin-build-tools-impl-2.0.0.pom">
            <sha256 value="21778645ed218ca2937782991610716826efdbd490dc8129e3534705fb6a1002" origin="Generated by Gradle" reason="A key couldn't be downloaded"/>
         </artifact>
      </component>
      <component group="org.jetbrains.kotlin" name="kotlin-compiler-embeddable" version="2.0.0">
         <artifact name="kotlin-compiler-embeddable-2.0.0.jar">
            <sha256 value="eb8ae09df38e212eec3965cafa97ab08112773fe2e870ebeb6131b8f69bfb92e" origin="Generated by Gradle" reason="A key couldn't be downloaded"/>
         </artifact>
         <artifact name="kotlin-compiler-embeddable-2.0.0.pom">
            <sha256 value="13c04c2c983a8faab531b64d0662db247fd35a1d88489330a1c29dc4a91e569e" origin="Generated by Gradle" reason="A key couldn't be downloaded"/>
         </artifact>
      </component>
      <component group="org.jetbrains.kotlin" name="kotlin-compiler-runner" version="2.0.0">
         <artifact name="kotlin-compiler-runner-2.0.0.jar">
            <sha256 value="18f22b00697b84ef45a41d2b0a572261f299eaa7dcdda819d8773948e4472474" origin="Generated by Gradle" reason="A key couldn't be downloaded"/>
         </artifact>
         <artifact name="kotlin-compiler-runner-2.0.0.pom">
            <sha256 value="42e6632358fa62be99bb8e4a278707e6b810dfc71ad3e5eea17e54ae39c83aac" origin="Generated by Gradle" reason="A key couldn't be downloaded"/>
         </artifact>
      </component>
      <component group="org.jetbrains.kotlin" name="kotlin-daemon-client" version="2.0.0">
         <artifact name="kotlin-daemon-client-2.0.0.jar">
            <sha256 value="dfa5ae84fc665b0478475fd9a63f2f984a9155ce1bfb4dc2abea278c6a0f2d94" origin="Generated by Gradle" reason="A key couldn't be downloaded"/>
         </artifact>
         <artifact name="kotlin-daemon-client-2.0.0.pom">
            <sha256 value="dbbc417fbbe94efab6a05a081d0f6336dacffa9d0426375e2a1781c57c5c2991" origin="Generated by Gradle" reason="A key couldn't be downloaded"/>
         </artifact>
      </component>
      <component group="org.jetbrains.kotlin" name="kotlin-daemon-embeddable" version="2.0.0">
         <artifact name="kotlin-daemon-embeddable-2.0.0.jar">
            <sha256 value="b907a36e9cfa587ca0523793d89eb2ea9bb545456935f180e12422486c14049f" origin="Generated by Gradle" reason="A key couldn't be downloaded"/>
         </artifact>
         <artifact name="kotlin-daemon-embeddable-2.0.0.pom">
            <sha256 value="ce23393a051fa5e94275854e12cee7ac1c1e9f641bd71ace81cba6fd54f9bc1a" origin="Generated by Gradle" reason="A key couldn't be downloaded"/>
         </artifact>
      </component>
      <component group="org.jetbrains.kotlin" name="kotlin-gradle-plugin" version="2.0.0">
         <artifact name="kotlin-gradle-plugin-2.0.0-gradle82.jar">
            <sha256 value="2899fbb6718325564159d2d1c51c9229d1eddde8356a3f7fb49a1b8f3f00a29d" origin="Generated by Gradle" reason="A key couldn't be downloaded"/>
         </artifact>
         <artifact name="kotlin-gradle-plugin-2.0.0.module">
            <sha256 value="e45806404e7e0c398a79bb5800205cb6ab2e4ad8d9b604170d33437c45351189" origin="Generated by Gradle" reason="A key couldn't be downloaded"/>
         </artifact>
      </component>
      <component group="org.jetbrains.kotlin" name="kotlin-gradle-plugin-annotations" version="2.0.0">
         <artifact name="kotlin-gradle-plugin-annotations-2.0.0.jar">
            <sha256 value="42b614cf70363be1195490e2567ad38cf26ccb32cf45db90509434e9621cb633" origin="Generated by Gradle" reason="A key couldn't be downloaded"/>
         </artifact>
         <artifact name="kotlin-gradle-plugin-annotations-2.0.0.pom">
            <sha256 value="214751a3993b10e16c72ef63f961f56d37a1c751aaef234e269172e1c40e528f" origin="Generated by Gradle" reason="A key couldn't be downloaded"/>
         </artifact>
      </component>
      <component group="org.jetbrains.kotlin" name="kotlin-gradle-plugin-api" version="2.0.0">
         <artifact name="kotlin-gradle-plugin-api-2.0.0-gradle82.jar">
            <sha256 value="f95693a82de0bbfb06d6b1eac364954b68bf488ba0c8cc2ff273976bb28ee223" origin="Generated by Gradle" reason="A key couldn't be downloaded"/>
         </artifact>
         <artifact name="kotlin-gradle-plugin-api-2.0.0.jar">
            <sha256 value="f95693a82de0bbfb06d6b1eac364954b68bf488ba0c8cc2ff273976bb28ee223" origin="Generated by Gradle" reason="A key couldn't be downloaded"/>
         </artifact>
         <artifact name="kotlin-gradle-plugin-api-2.0.0.module">
            <sha256 value="9f6ac6f6dcb3c3d933fde92e4de93381b78d3212ae68eb66702da812bf6ecfa9" origin="Generated by Gradle" reason="A key couldn't be downloaded"/>
         </artifact>
      </component>
      <component group="org.jetbrains.kotlin" name="kotlin-gradle-plugin-idea" version="2.0.0">
         <artifact name="kotlin-gradle-plugin-idea-2.0.0.jar">
            <sha256 value="c1f4ea0c19267f1eed474b541b07715c49167acfbf027a8a2fd07cbbc81b8e72" origin="Generated by Gradle" reason="A key couldn't be downloaded"/>
         </artifact>
         <artifact name="kotlin-gradle-plugin-idea-2.0.0.module">
            <sha256 value="4163bd47a34ba1bd74c323577fe8426b78d5662b760658106352b791bad4dcf8" origin="Generated by Gradle" reason="A key couldn't be downloaded"/>
         </artifact>
      </component>
      <component group="org.jetbrains.kotlin" name="kotlin-gradle-plugin-idea-proto" version="2.0.0">
         <artifact name="kotlin-gradle-plugin-idea-proto-2.0.0.jar">
            <sha256 value="51d31fe50bc89ac080d49bc87cc77f139586cfcb1098d4aaafbbc72a71d8e207" origin="Generated by Gradle" reason="A key couldn't be downloaded"/>
         </artifact>
         <artifact name="kotlin-gradle-plugin-idea-proto-2.0.0.pom">
            <sha256 value="acbec7892f527cb610b62493551221e4d0d08e0b38973464bd6d747f1bab227a" origin="Generated by Gradle" reason="A key couldn't be downloaded"/>
         </artifact>
      </component>
      <component group="org.jetbrains.kotlin" name="kotlin-gradle-plugin-model" version="2.0.0">
         <artifact name="kotlin-gradle-plugin-model-2.0.0.jar">
            <sha256 value="b7b436caef0b0d5f571ddd88214418cf8580a34ec8e81f22503cef35755552d9" origin="Generated by Gradle" reason="A key couldn't be downloaded"/>
         </artifact>
         <artifact name="kotlin-gradle-plugin-model-2.0.0.module">
            <sha256 value="ecc56ff4219215ae9626e06d51aa9a3ef59bf5e6d4509260328593c059805b06" origin="Generated by Gradle" reason="A key couldn't be downloaded"/>
         </artifact>
      </component>
      <component group="org.jetbrains.kotlin" name="kotlin-gradle-plugins-bom" version="2.0.0">
         <artifact name="kotlin-gradle-plugins-bom-2.0.0.module">
            <sha256 value="eab8df114dc10987acd3093ca2ae310b753a13b718a263d5b5d83a6595c04bda" origin="Generated by Gradle" reason="A key couldn't be downloaded"/>
         </artifact>
         <artifact name="kotlin-gradle-plugins-bom-2.0.0.pom">
            <sha256 value="c4a0586af77f0fb4f7e367033a02ac718beff0d0193cc7989583a982aa2752f2" origin="Generated by Gradle" reason="A key couldn't be downloaded"/>
         </artifact>
      </component>
      <component group="org.jetbrains.kotlin" name="kotlin-klib-commonizer-api" version="2.0.0">
         <artifact name="kotlin-klib-commonizer-api-2.0.0.jar">
            <sha256 value="1e1b57dc1f802aa778f5f46054a253213d8b03c58357e347f08222a2d1950175" origin="Generated by Gradle" reason="A key couldn't be downloaded"/>
         </artifact>
         <artifact name="kotlin-klib-commonizer-api-2.0.0.pom">
            <sha256 value="72aea51ffd69e7a6d7de7e2ca9ac192c69918f5a0339974caf5e9fa4c762cd58" origin="Generated by Gradle" reason="A key couldn't be downloaded"/>
         </artifact>
      </component>
      <component group="org.jetbrains.kotlin" name="kotlin-klib-commonizer-embeddable" version="2.0.0">
         <artifact name="kotlin-klib-commonizer-embeddable-2.0.0.jar">
            <sha256 value="687bca71931939389e9d0200f95ecc1508e0d41851ede51f4610f876d037a1dd" origin="Generated by Gradle" reason="A key couldn't be downloaded"/>
         </artifact>
         <artifact name="kotlin-klib-commonizer-embeddable-2.0.0.pom">
            <sha256 value="7aab0a39bad95150823df619659fc49ba951de0b7dfa683fce27bcea18da3c9e" origin="Generated by Gradle" reason="A key couldn't be downloaded"/>
         </artifact>
      </component>
      <component group="org.jetbrains.kotlin" name="kotlin-native-prebuilt" version="2.0.0">
         <artifact name="kotlin-native-prebuilt-2.0.0-macos-aarch64.tar.gz">
            <sha256 value="d60bea435a0b23fd1bb1b4ad6ae50c778b52cf300cb3421471b252e44bf184c5" origin="Generated by Gradle" reason="A key couldn't be downloaded"/>
         </artifact>
         <artifact name="kotlin-native-prebuilt-2.0.0.pom">
            <sha256 value="c83bc3c52dd174531b5dd48e167e00fcaa9a1459752e8ce21d9e381b893af406" origin="Generated by Gradle" reason="A key couldn't be downloaded"/>
         </artifact>
      </component>
      <component group="org.jetbrains.kotlin" name="kotlin-native-utils" version="2.0.0">
         <artifact name="kotlin-native-utils-2.0.0.jar">
            <sha256 value="20d5904b4f0fa20624cab109ae303dff039142651b77901e0e14aae5feeb0ae6" origin="Generated by Gradle" reason="A key couldn't be downloaded"/>
         </artifact>
         <artifact name="kotlin-native-utils-2.0.0.pom">
            <sha256 value="56317d6fc49729f42e935d1f8c9769d3ad855264563a57a691503ba80ae3d452" origin="Generated by Gradle" reason="A key couldn't be downloaded"/>
         </artifact>
      </component>
      <component group="org.jetbrains.kotlin" name="kotlin-reflect" version="1.6.10">
         <artifact name="kotlin-reflect-1.6.10.jar">
            <sha256 value="3277ac102ae17aad10a55abec75ff5696c8d109790396434b496e75087854203" origin="Generated by Gradle" reason="A key couldn't be downloaded"/>
         </artifact>
         <artifact name="kotlin-reflect-1.6.10.pom">
            <sha256 value="57905524274a00ae028aaccc27283f6bc5925a934a046c1cc5d06c8ee4d6d5a9" origin="Generated by Gradle" reason="A key couldn't be downloaded"/>
         </artifact>
      </component>
      <component group="org.jetbrains.kotlin" name="kotlin-reflect" version="1.8.22">
         <artifact name="kotlin-reflect-1.8.22.jar">
            <sha256 value="655825fa6511220fed0cae5aad4dfea2abf98fd10f0ae77eb8daf6abfcd0f027" origin="Generated by Gradle" reason="A key couldn't be downloaded"/>
         </artifact>
         <artifact name="kotlin-reflect-1.8.22.pom">
            <sha256 value="29e1ea08a3d3ab482d1fdfd41fbe9345912df466dbafafb4b12d1837c72be328" origin="Generated by Gradle" reason="A key couldn't be downloaded"/>
         </artifact>
      </component>
      <component group="org.jetbrains.kotlin" name="kotlin-reflect" version="2.0.0">
         <artifact name="kotlin-reflect-2.0.0.jar">
            <sha256 value="111bd906921937f76da17760641116d04b57a7a12fcf980efe7c6767f45179f0" origin="Generated by Gradle" reason="A key couldn't be downloaded"/>
         </artifact>
         <artifact name="kotlin-reflect-2.0.0.pom">
            <sha256 value="8a442b9ece3e56df9f126f31c62a1d2a31248abec288b6d830bae772371848b0" origin="Generated by Gradle" reason="A key couldn't be downloaded"/>
         </artifact>
      </component>
      <component group="org.jetbrains.kotlin" name="kotlin-script-runtime" version="2.0.0">
         <artifact name="kotlin-script-runtime-2.0.0.jar">
            <sha256 value="b57a14387a504f1d3d8634899a830cb0bc5fe1adb86a62cc65d940fe982b04f9" origin="Generated by Gradle" reason="A key couldn't be downloaded"/>
         </artifact>
         <artifact name="kotlin-script-runtime-2.0.0.pom">
            <sha256 value="e7540d47f555359526927b747aa47323f9897b94f72eb8ce451e36de752533db" origin="Generated by Gradle" reason="A key couldn't be downloaded"/>
         </artifact>
      </component>
      <component group="org.jetbrains.kotlin" name="kotlin-scripting-common" version="2.0.0">
         <artifact name="kotlin-scripting-common-2.0.0.jar">
            <sha256 value="3cb9f18af2409c90793dfc6ce265a1a9268df4c7e5de3e2a2bcee7ec86059179" origin="Generated by Gradle" reason="A key couldn't be downloaded"/>
         </artifact>
         <artifact name="kotlin-scripting-common-2.0.0.pom">
            <sha256 value="97283d9b9908d89039cd6e40df6dd810e9aa144c4320eae6b6310a8b6eecee50" origin="Generated by Gradle" reason="A key couldn't be downloaded"/>
         </artifact>
      </component>
      <component group="org.jetbrains.kotlin" name="kotlin-scripting-compiler-embeddable" version="2.0.0">
         <artifact name="kotlin-scripting-compiler-embeddable-2.0.0.jar">
            <sha256 value="1f914b74e4e135d52478d63210570f90dab04cc6a6f7d54e1f3ea8cf57a1a754" origin="Generated by Gradle" reason="A key couldn't be downloaded"/>
         </artifact>
         <artifact name="kotlin-scripting-compiler-embeddable-2.0.0.pom">
            <sha256 value="072ff8c68f0a522837fa2c667071fbf7a7b3d9d6d3bc3b58d5a92f20d0af7c9b" origin="Generated by Gradle" reason="A key couldn't be downloaded"/>
         </artifact>
      </component>
      <component group="org.jetbrains.kotlin" name="kotlin-scripting-compiler-impl-embeddable" version="2.0.0">
         <artifact name="kotlin-scripting-compiler-impl-embeddable-2.0.0.jar">
            <sha256 value="98de5f7838914e6880ecaef3a6e08e5cb165f16629afa0a2df3550cf7f22d2bf" origin="Generated by Gradle" reason="A key couldn't be downloaded"/>
         </artifact>
         <artifact name="kotlin-scripting-compiler-impl-embeddable-2.0.0.pom">
            <sha256 value="5bf861970ba3f7320df97e4e423727ae405aee331adf86486bbeb96eed908dc8" origin="Generated by Gradle" reason="A key couldn't be downloaded"/>
         </artifact>
      </component>
      <component group="org.jetbrains.kotlin" name="kotlin-scripting-jvm" version="2.0.0">
         <artifact name="kotlin-scripting-jvm-2.0.0.jar">
            <sha256 value="7f20010fba093904eed7a8b84938bf9934be4747ef25f676d17bc301bd139a62" origin="Generated by Gradle" reason="A key couldn't be downloaded"/>
         </artifact>
         <artifact name="kotlin-scripting-jvm-2.0.0.pom">
            <sha256 value="0499bd736d62273065604f65b1632d5a0f2ff1b0309f079f0840f7f6e17ca107" origin="Generated by Gradle" reason="A key couldn't be downloaded"/>
         </artifact>
      </component>
      <component group="org.jetbrains.kotlin" name="kotlin-serialization" version="2.0.0">
         <artifact name="kotlin-serialization-2.0.0-gradle82.jar">
            <sha256 value="4784dbb454cc3acbe1bb6ee781ea6c55e24afc1b2de9146d110437460460f88f" origin="Generated by Gradle" reason="A key couldn't be downloaded"/>
         </artifact>
         <artifact name="kotlin-serialization-2.0.0.module">
            <sha256 value="9010cadc0e9b8fd90661514af774d10390e7cc1b8ebc286c5636f45697b4bfec" origin="Generated by Gradle" reason="A key couldn't be downloaded"/>
         </artifact>
      </component>
      <component group="org.jetbrains.kotlin" name="kotlin-serialization-compiler-plugin-embeddable" version="2.0.0">
         <artifact name="kotlin-serialization-compiler-plugin-embeddable-2.0.0.jar">
            <sha256 value="3bf895c69edf167660b857ca1e2f3241316e9c8c30810a04d91ee9bfa5351799" origin="Generated by Gradle" reason="A key couldn't be downloaded"/>
         </artifact>
         <artifact name="kotlin-serialization-compiler-plugin-embeddable-2.0.0.pom">
            <sha256 value="e05a10a39c78da920c85fcc17d1c8a8d96c0f4cbf04a84d4f93b82bba38dd0f9" origin="Generated by Gradle" reason="A key couldn't be downloaded"/>
         </artifact>
      </component>
      <component group="org.jetbrains.kotlin" name="kotlin-stdlib" version="1.9.10">
         <artifact name="kotlin-stdlib-1.9.10.jar">
            <sha256 value="55e989c512b80907799f854309f3bc7782c5b3d13932442d0379d5c472711504" origin="Generated by Gradle" reason="A key couldn't be downloaded"/>
         </artifact>
         <artifact name="kotlin-stdlib-1.9.10.pom">
            <sha256 value="7e29fbf73fdf71e0679d3dee7e680fd573464fa01644a4f58ab819d2c088d3d2" origin="Generated by Gradle" reason="A key couldn't be downloaded"/>
         </artifact>
      </component>
      <component group="org.jetbrains.kotlin" name="kotlin-stdlib" version="2.0.0">
         <artifact name="kotlin-stdlib-2.0.0-all.jar">
            <sha256 value="30e05222bc067fffb896a3276b5f1e3f29450bf1d9461d27a19ce0efc793b5cd" origin="Generated by Gradle" reason="A key couldn't be downloaded"/>
         </artifact>
         <artifact name="kotlin-stdlib-2.0.0-sources.jar">
            <sha256 value="256f2c1caf3df558d6c41b79fb83add98edcc08436b821a80b5f17d806c664a1" origin="Generated by Gradle" reason="A key couldn't be downloaded"/>
         </artifact>
         <artifact name="kotlin-stdlib-2.0.0.jar">
            <sha256 value="240938c4aab8e73e888703e3e7d3f87383ffe5bd536d6d5e3c100d4cd0379fcf" origin="Generated by Gradle" reason="A key couldn't be downloaded"/>
         </artifact>
         <artifact name="kotlin-stdlib-2.0.0.module">
            <sha256 value="64f96ea8e7b9896731052241ffd3a265f8274d761e5fe9dc088ac45b31718341" origin="Generated by Gradle" reason="A key couldn't be downloaded"/>
         </artifact>
      </component>
      <component group="org.jetbrains.kotlin" name="kotlin-stdlib-common" version="1.9.10">
         <artifact name="kotlin-stdlib-common-1.9.10.jar">
            <sha256 value="cde3341ba18a2ba262b0b7cf6c55b20c90e8d434e42c9a13e6a3f770db965a88" origin="Generated by Gradle" reason="A key couldn't be downloaded"/>
         </artifact>
         <artifact name="kotlin-stdlib-common-1.9.10.pom">
            <sha256 value="7d4b70547910676b3bdfc8925a88f3b6bfb24582c9784542805544ceef490a92" origin="Generated by Gradle" reason="A key couldn't be downloaded"/>
         </artifact>
      </component>
      <component group="org.jetbrains.kotlin" name="kotlin-stdlib-common" version="2.0.0">
         <artifact name="kotlin-stdlib-common-2.0.0.module">
            <sha256 value="2335187440c51d0d69e1b906fefc31f6169691c8598177b0e610c9b9a92ce6b5" origin="Generated by Gradle" reason="A key couldn't be downloaded"/>
         </artifact>
      </component>
      <component group="org.jetbrains.kotlin" name="kotlin-stdlib-jdk7" version="1.8.21">
         <artifact name="kotlin-stdlib-jdk7-1.8.21.pom">
            <sha256 value="9bb107d5d5e3930bc5977f007a43cd20b7d24d91b1c1e528ea6ee0f248f14d36" origin="Generated by Gradle" reason="A key couldn't be downloaded"/>
         </artifact>
      </component>
      <component group="org.jetbrains.kotlin" name="kotlin-stdlib-jdk7" version="1.8.22">
         <artifact name="kotlin-stdlib-jdk7-1.8.22.jar">
            <sha256 value="055f5cb24287fa106100995a7b47ab92126b81e832e875f5fa2cf0bd55693d0b" origin="Generated by Gradle" reason="A key couldn't be downloaded"/>
         </artifact>
         <artifact name="kotlin-stdlib-jdk7-1.8.22.pom">
            <sha256 value="4f958aa993d5984f8f5ebed4146562a5f3a9f695b6049c9f287381379cadab33" origin="Generated by Gradle" reason="A key couldn't be downloaded"/>
         </artifact>
      </component>
      <component group="org.jetbrains.kotlin" name="kotlin-stdlib-jdk7" version="1.9.10">
         <artifact name="kotlin-stdlib-jdk7-1.9.10.jar">
            <sha256 value="ac6361bf9ad1ed382c2103d9712c47cdec166232b4903ed596e8876b0681c9b7" origin="Generated by Gradle" reason="A key couldn't be downloaded"/>
         </artifact>
         <artifact name="kotlin-stdlib-jdk7-1.9.10.pom">
            <sha256 value="c7fa67c7961320b89d85a3ca59a2e18c2c65850845595dcae4b46af6945edcd5" origin="Generated by Gradle" reason="A key couldn't be downloaded"/>
         </artifact>
      </component>
      <component group="org.jetbrains.kotlin" name="kotlin-stdlib-jdk8" version="1.7.21">
         <artifact name="kotlin-stdlib-jdk8-1.7.21.pom">
            <sha256 value="6f3b9343c412d6ae40a4c78fb8a70986496450a9528cdbac7629a88e1aa58389" origin="Generated by Gradle" reason="A key couldn't be downloaded"/>
         </artifact>
      </component>
      <component group="org.jetbrains.kotlin" name="kotlin-stdlib-jdk8" version="1.8.0">
         <artifact name="kotlin-stdlib-jdk8-1.8.0.pom">
            <sha256 value="2bb6c7551b97c7ba029f9866582e7aa19d63abfd4cd53da3fc0c462f3ab5fc26" origin="Generated by Gradle" reason="A key couldn't be downloaded"/>
         </artifact>
      </component>
      <component group="org.jetbrains.kotlin" name="kotlin-stdlib-jdk8" version="1.8.21">
         <artifact name="kotlin-stdlib-jdk8-1.8.21.pom">
            <sha256 value="3839d728d7c309a5c368b0270b44b4f1c7878ff5ca5d32a9a204faa3491459d8" origin="Generated by Gradle" reason="A key couldn't be downloaded"/>
         </artifact>
      </component>
      <component group="org.jetbrains.kotlin" name="kotlin-stdlib-jdk8" version="1.8.22">
         <artifact name="kotlin-stdlib-jdk8-1.8.22.jar">
            <sha256 value="4198b0eaf090a4f25b6f7e5a59581f4314ba8c9f6cd1d13ee9d348e65ed8f707" origin="Generated by Gradle" reason="A key couldn't be downloaded"/>
         </artifact>
         <artifact name="kotlin-stdlib-jdk8-1.8.22.pom">
            <sha256 value="928f2187217476313cb816d48070bc7654aa3b9a5ae81d3fc5f8c279cc8f8d9e" origin="Generated by Gradle" reason="A key couldn't be downloaded"/>
         </artifact>
      </component>
      <component group="org.jetbrains.kotlin" name="kotlin-stdlib-jdk8" version="1.9.10">
         <artifact name="kotlin-stdlib-jdk8-1.9.10.jar">
            <sha256 value="a4c74d94d64ce1abe53760fe0389dd941f6fc558d0dab35e47c085a11ec80f28" origin="Generated by Gradle" reason="A key couldn't be downloaded"/>
         </artifact>
         <artifact name="kotlin-stdlib-jdk8-1.9.10.pom">
            <sha256 value="5f4b94dd3065a7764c37fa15de2ad6d81f40d59f8cb33f17d181c6384fb7a72e" origin="Generated by Gradle" reason="A key couldn't be downloaded"/>
         </artifact>
      </component>
      <component group="org.jetbrains.kotlin" name="kotlin-test" version="2.0.0">
         <artifact name="kotlin-test-2.0.0-all.jar">
            <sha256 value="3288873963471c51e2ea54a690f605b291b03022675cf0c040080adefbb37010" origin="Generated by Gradle" reason="A key couldn't be downloaded"/>
         </artifact>
         <artifact name="kotlin-test-2.0.0.jar">
            <sha256 value="8438cc11769da31cbb4445dfafd12c08cf4015daa387963106f121a85a56864c" origin="Generated by Gradle" reason="A key couldn't be downloaded"/>
         </artifact>
         <artifact name="kotlin-test-2.0.0.module">
            <sha256 value="53c0f17a1388041cdf8578fdc425dc717221f177c8c839fb2930a08951aa1d25" origin="Generated by Gradle" reason="A key couldn't be downloaded"/>
         </artifact>
      </component>
      <component group="org.jetbrains.kotlin" name="kotlin-test-junit" version="2.0.0">
         <artifact name="kotlin-test-junit-2.0.0-sources.jar">
            <sha256 value="c411a0dad1218f3f652b6619f228fefee498903ee6e11c36c990fbc3fe823f18" origin="Generated by Gradle" reason="A key couldn't be downloaded"/>
         </artifact>
         <artifact name="kotlin-test-junit-2.0.0.jar">
            <sha256 value="0dc4d83c3c32bb5e1fc82d9263767c564ad860ff2aa4ac640899c8f4a8ef1814" origin="Generated by Gradle" reason="A key couldn't be downloaded"/>
         </artifact>
         <artifact name="kotlin-test-junit-2.0.0.module">
            <sha256 value="a056a15e6ff6d189e67ca5b271d24f851c0f00e3ec5a31970d8276b1bf9ac45e" origin="Generated by Gradle" reason="A key couldn't be downloaded"/>
         </artifact>
      </component>
      <component group="org.jetbrains.kotlin" name="kotlin-tooling-core" version="2.0.0">
         <artifact name="kotlin-tooling-core-2.0.0.jar">
            <sha256 value="73464aa3c214567013a4373f09e7b6f0b63185b3a6df6988b347430d7777a971" origin="Generated by Gradle" reason="A key couldn't be downloaded"/>
         </artifact>
         <artifact name="kotlin-tooling-core-2.0.0.pom">
            <sha256 value="cf6255cbe64be5cfad16dd9a037e504264496c57c4f755e2f3527ab45aa166ba" origin="Generated by Gradle" reason="A key couldn't be downloaded"/>
         </artifact>
      </component>
      <component group="org.jetbrains.kotlin" name="kotlin-util-io" version="2.0.0">
         <artifact name="kotlin-util-io-2.0.0.jar">
            <sha256 value="088e45d9522db6406f0b1e4ed328389c9b5992a9567cd91b57ae21c1b9221610" origin="Generated by Gradle" reason="A key couldn't be downloaded"/>
         </artifact>
         <artifact name="kotlin-util-io-2.0.0.pom">
            <sha256 value="c2cf75fd427eb63b7d321f4f10914675fe63320a90595f465a82cc5a1b64f4f7" origin="Generated by Gradle" reason="A key couldn't be downloaded"/>
         </artifact>
      </component>
      <component group="org.jetbrains.kotlin" name="kotlin-util-klib" version="2.0.0">
         <artifact name="kotlin-util-klib-2.0.0.jar">
            <sha256 value="95f1a677e8d24bc0b32e76783ef173c5c0e09ed41b50471736d6599bed19d875" origin="Generated by Gradle" reason="A key couldn't be downloaded"/>
         </artifact>
         <artifact name="kotlin-util-klib-2.0.0.pom">
            <sha256 value="0b9321f812048eecd0391765c882188fb7ea0f30ea84f8cf6874ab58371ee21f" origin="Generated by Gradle" reason="A key couldn't be downloaded"/>
         </artifact>
      </component>
      <component group="org.jetbrains.kotlin.jvm" name="org.jetbrains.kotlin.jvm.gradle.plugin" version="2.0.0">
         <artifact name="org.jetbrains.kotlin.jvm.gradle.plugin-2.0.0.pom">
            <sha256 value="e48cc51526cf45e2dfe7dee2b9a71bbb39cc7742fb2f068fc57fb3a19a09fdd6" origin="Generated by Gradle" reason="Artifact is not signed"/>
         </artifact>
      </component>
      <component group="org.jetbrains.kotlin.plugin.serialization" name="org.jetbrains.kotlin.plugin.serialization.gradle.plugin" version="2.0.0">
         <artifact name="org.jetbrains.kotlin.plugin.serialization.gradle.plugin-2.0.0.pom">
            <sha256 value="4dc4bb84f9ea40a2d006854887a39bf8001b9254b60fc855869240a97c721662" origin="Generated by Gradle" reason="Artifact is not signed"/>
         </artifact>
      </component>
      <component group="org.ow2" name="ow2" version="1.5">
         <artifact name="ow2-1.5.pom">
            <sha256 value="0f8a1b116e760b8fe6389c51b84e4b07a70fc11082d4f936e453b583dd50b43b" origin="Generated by Gradle" reason="Artifact is not signed"/>
         </artifact>
      </component>
      <component group="org.ow2" name="ow2" version="1.5.1">
         <artifact name="ow2-1.5.1.pom">
            <pgp value="10f3c7a02eca55e502badcf3991efb94db91127d"/>
         </artifact>
      </component>
      <component group="org.sonarqube" name="org.sonarqube.gradle.plugin" version="6.2.0.5505">
         <artifact name="org.sonarqube.gradle.plugin-6.2.0.5505.pom">
            <sha256 value="ad15fa6ac0e40aa7e09892f4e393c3c8847aef9f3ac117670b7081362b6eef02" origin="Generated by Gradle" reason="Artifact is not signed"/>
         </artifact>
      </component>
      <component group="org.sonatype.oss" name="oss-parent" version="7">
         <artifact name="oss-parent-7.pom">
            <sha256 value="b51f8867c92b6a722499557fc3a1fdea77bdf9ef574722fe90ce436a29559454" origin="Generated by Gradle" reason="Artifact is not signed"/>
         </artifact>
      </component>
      <component group="org.sonatype.oss" name="oss-parent" version="9">
         <artifact name="oss-parent-9.pom">
            <pgp value="44fbdbbc1a00fe414f1c1873586654072ead6677"/>
         </artifact>
      </component>
   </components>
</verification-metadata>
